[
  {
    "match_id": 538001,
    "utc_date": "2026-01-17T12:30:00Z",
    "home": "Manchester United FC",
    "away": "Manchester City FC"
  },
  {
    "match_id": 537995,
    "utc_date": "2026-01-17T15:00:00Z",
    "home": "Sunderland AFC",
    "away": "Crystal Palace FC"
  },
  {
    "match_id": 537998,
    "utc_date": "2026-01-17T15:00:00Z",
    "home": "Chelsea FC",
    "away": "Brentford FC"
  },
  {
    "match_id": 537999,
    "utc_date": "2026-01-17T15:00:00Z",
    "home": "Liverpool FC",
    "away": "Burnley FC"
  },
  {
    "match_id": 538000,
    "utc_date": "2026-01-17T15:00:00Z",
    "home": "Leeds United FC",
    "away": "Fulham FC"
  },
  {
    "match_id": 538003,
    "utc_date": "2026-01-17T15:00:00Z",
    "home": "Tottenham Hotspur FC",
    "away": "West Ham United FC"
  },
  {
    "match_id": 538002,
    "utc_date": "2026-01-17T17:30:00Z",
    "home": "Nottingham Forest FC",
    "away": "Arsenal FC"
  },
  {
    "match_id": 538004,
    "utc_date": "2026-01-18T14:00:00Z",
    "home": "Wolverhampton Wanderers FC",
    "away": "Newcastle United FC"
  },
  {
    "match_id": 537996,
    "utc_date": "2026-01-18T16:30:00Z",
    "home": "Aston Villa FC",
    "away": "Everton FC"
  },
  {
    "match_id": 537997,
    "utc_date": "2026-01-19T20:00:00Z",
    "home": "Brighton & Hove Albion FC",
    "away": "AFC Bournemouth"
  },
  {
    "match_id": 538014,
    "utc_date": "2026-01-24T12:30:00Z",
    "home": "West Ham United FC",
    "away": "Sunderland AFC"
  },
  {
    "match_id": 538009,
    "utc_date": "2026-01-24T15:00:00Z",
    "home": "Burnley FC",
    "away": "Tottenham Hotspur FC"
  },
  {
    "match_id": 538011,
    "utc_date": "2026-01-24T15:00:00Z",
    "home": "Fulham FC",
    "away": "Brighton & Hove Albion FC"
  },
  {
    "match_id": 538012,
    "utc_date": "2026-01-24T15:00:00Z",
    "home": "Manchester City FC",
    "away": "Wolverhampton Wanderers FC"
  },
  {
    "match_id": 538005,
    "utc_date": "2026-01-24T17:30:00Z",
    "home": "AFC Bournemouth",
    "away": "Liverpool FC"
  },
  {
    "match_id": 538006,
    "utc_date": "2026-01-25T14:00:00Z",
    "home": "Crystal Palace FC",
    "away": "Chelsea FC"
  },
  {
    "match_id": 538008,
    "utc_date": "2026-01-25T14:00:00Z",
    "home": "Brentford FC",
    "away": "Nottingham Forest FC"
  },
  {
    "match_id": 538013,
    "utc_date": "2026-01-25T14:00:00Z",
    "home": "Newcastle United FC",
    "away": "Aston Villa FC"
  },
  {
    "match_id": 538007,
    "utc_date": "2026-01-25T16:30:00Z",
    "home": "Arsenal FC",
    "away": "Manchester United FC"
  },
  {
    "match_id": 538010,
    "utc_date": "2026-01-26T20:00:00Z",
    "home": "Everton FC",
    "away": "Leeds United FC"
  },
  {
    "match_id": 538017,
    "utc_date": "2026-01-31T15:00:00Z",
    "home": "Brighton & Hove Albion FC",
    "away": "Everton FC"
  },
  {
    "match_id": 538020,
    "utc_date": "2026-01-31T15:00:00Z",
    "home": "Leeds United FC",
    "away": "Arsenal FC"
  },
  {
    "match_id": 538024,
    "utc_date": "2026-01-31T15:00:00Z",
    "home": "Wolverhampton Wanderers FC",
    "away": "AFC Bournemouth"
  },
  {
    "match_id": 538018,
    "utc_date": "2026-01-31T17:30:00Z",
    "home": "Chelsea FC",
    "away": "West Ham United FC"
  },
  {
    "match_id": 538019,
    "utc_date": "2026-01-31T20:00:00Z",
    "home": "Liverpool FC",
    "away": "Newcastle United FC"
  },
  {
    "match_id": 538016,
    "utc_date": "2026-02-01T14:00:00Z",
    "home": "Aston Villa FC",
    "away": "Brentford FC"
  },
  {
    "match_id": 538021,
    "utc_date": "2026-02-01T14:00:00Z",
    "home": "Manchester United FC",
    "away": "Fulham FC"
  },
  {
    "match_id": 538022,
    "utc_date": "2026-02-01T14:00:00Z",
    "home": "Nottingham Forest FC",
    "away": "Crystal Palace FC"
  },
  {
    "match_id": 538023,
    "utc_date": "2026-02-01T16:30:00Z",
    "home": "Tottenham Hotspur FC",
    "away": "Manchester City FC"
  },
  {
    "match_id": 538015,
    "utc_date": "2026-02-02T20:00:00Z",
    "home": "Sunderland AFC",
    "away": "Burnley FC"
  }
]